Metadata-Version: 2.1
Name: limnoria-webstats
Version: 0.5
Summary: UNKNOWN
Home-page: http://supybot.fr.cr/WebStats
Author: Valentin Lorentz
Author-email: progval@gmail.com
License: UNKNOWN
Platform: UNKNOWN
Classifier: Environment :: Plugins
Classifier: Programming Language :: Python :: 3
Classifier: Topic :: Communications :: Chat
